modal/__init__.py
modal/__main__.py
modal/_billing.py
modal/_clustered_functions.py
modal/_clustered_functions.pyi
modal/_container_entrypoint.py
modal/_functions.py
modal/_ipython.py
modal/_location.py
modal/_object.py
modal/_output.py
modal/_partial_function.py
modal/_pty.py
modal/_resolver.py
modal/_resources.py
modal/_serialization.py
modal/_traceback.py
modal/_tunnel.py
modal/_tunnel.pyi
modal/_type_manager.py
modal/_watcher.py
modal/app.py
modal/app.pyi
modal/billing.py
modal/call_graph.py
modal/client.py
modal/client.pyi
modal/cloud_bucket_mount.py
modal/cloud_bucket_mount.pyi
modal/cls.py
modal/cls.pyi
modal/config.py
modal/container_process.py
modal/container_process.pyi
modal/dict.py
modal/dict.pyi
modal/environments.py
modal/environments.pyi
modal/exception.py
modal/file_io.py
modal/file_io.pyi
modal/file_pattern_matcher.py
modal/functions.py
modal/functions.pyi
modal/gpu.py
modal/image.py
modal/image.pyi
modal/io_streams.py
modal/io_streams.pyi
modal/mount.py
modal/mount.pyi
modal/network_file_system.py
modal/network_file_system.pyi
modal/object.py
modal/object.pyi
modal/output.py
modal/parallel_map.py
modal/parallel_map.pyi
modal/partial_function.py
modal/partial_function.pyi
modal/proxy.py
modal/proxy.pyi
modal/py.typed
modal/queue.py
modal/queue.pyi
modal/retries.py
modal/runner.py
modal/runner.pyi
modal/running_app.py
modal/sandbox.py
modal/sandbox.pyi
modal/schedule.py
modal/scheduler_placement.py
modal/secret.py
modal/secret.pyi
modal/serving.py
modal/serving.pyi
modal/snapshot.py
modal/snapshot.pyi
modal/stream_type.py
modal/token_flow.py
modal/token_flow.pyi
modal/volume.py
modal/volume.pyi
modal/_runtime/__init__.py
modal/_runtime/asgi.py
modal/_runtime/container_io_manager.py
modal/_runtime/container_io_manager.pyi
modal/_runtime/execution_context.py
modal/_runtime/execution_context.pyi
modal/_runtime/gpu_memory_snapshot.py
modal/_runtime/telemetry.py
modal/_runtime/user_code_imports.py
modal/_utils/__init__.py
modal/_utils/app_utils.py
modal-1.2.0.dist-info/licenses/LICENSE
modal-1.2.0.dist-info/METADATA
modal-1.2.0.dist-info/WHEEL
modal-1.2.0.dist-info/entry_points.txt
modal-1.2.0.dist-info/top_level.txt
modal-1.2.0.dist-info/RECORD
